__init__.py
automl/__init__.py
automl/auto_classification.py
automl/auto_regression.py
automl/automl.py
automl/classifiers.py
automl/regressors.py
automl/scalers_transformers.py
automl/utils/__init__.py
automl/utils/function_helper.py
automl/utils/grouped_train_test_splitter.py
automl/utils/misc.py
py_automl_lib-2.2.9.dist-info/licenses/LICENSE
py_automl_lib-2.2.9.dist-info/METADATA
py_automl_lib-2.2.9.dist-info/WHEEL
py_automl_lib-2.2.9.dist-info/top_level.txt
py_automl_lib-2.2.9.dist-info/RECORD
