Metadata-Version: 2.4
Name: py-automl-lib
Version: 2.2.9
Summary: Python package for automated hyperparameter-optimization of common machine-learning algorithms
Author: Owen O'D
Project-URL: Homepage, https://github.com/owenodriscoll/AutoML
Classifier: Programming Language :: Python :: 3.11
Classifier: License :: OSI Approved :: MIT License
Classifier: Operating System :: OS Independent
Requires-Python: <3.13.0,>=3.11.0
License-File: LICENSE
Requires-Dist: catboost
Requires-Dist: xgboost
Requires-Dist: lightgbm
Requires-Dist: optuna
Requires-Dist: scikit-learn
Requires-Dist: numpy
Requires-Dist: pandas
Requires-Dist: SQLAlchemy
Requires-Dist: timeout-decorator
Requires-Dist: fastparquet
Requires-Dist: pyarrow
Provides-Extra: shap
Requires-Dist: shap; extra == "shap"
Dynamic: license-file
